{
  "meta": {
    "generated_at": "2026-06-19T14:58:55.443507+00:00",
    "source": "https://nmsgalactichub.miraheze.org/w/api.php",
    "table": "Minerals",
    "count": 104,
    "available_fields": [
      "_pageName=Page",
      "Name",
      "Image",
      "Galaxy",
      "Glyphs",
      "Civilized=Civilization",
      "Discovered=DiscoveredBy",
      "DiscoveredLink=DiscovererPage"
    ]
  },
  "items": [
    {
      "page": "Abswuite",
      "page_url": "https://nmsgalactichub.miraheze.org/wiki/Abswuite",
      "name": "Abswuite",
      "image_name": "Absw1.jpg",
      "image_url": "https://static.wikitide.net/nmsgalactichubwiki/0/0e/Absw1.jpg",
      "galaxy": "Euclid",
      "glyphs": "3051F9556C2F",
      "civilization": "Legacy Galactic Hub",
      "discovered_by": "",
      "discoverer_page": "Donrhowland",
      "discoverer_url": "https://nmsgalactichub.miraheze.org/wiki/Donrhowland"
    },
    {
      "page": "Ajakaite",
      "page_url": "https://nmsgalactichub.miraheze.org/wiki/Ajakaite",
      "name": "Ajakaite",
      "image_name": "Screenshot (3184).png",
      "image_url": "https://static.wikitide.net/nmsgalactichubwiki/c/ca/Screenshot_%283184%29.png",
      "galaxy": "Calypso",
      "glyphs": "2220F9556C2F",
      "civilization": "Galactic Hub Calypso",
      "discovered_by": "",
      "discoverer_page": "Randomner",
      "discoverer_url": "https://nmsgalactichub.miraheze.org/wiki/Randomner"
    },
    {
      "page": "Alquiite",
      "page_url": "https://nmsgalactichub.miraheze.org/wiki/Alquiite",
      "name": "Alquiite",
      "image_name": "AlquiiteMain.jpg",
      "image_url": "https://static.wikitide.net/nmsgalactichubwiki/a/a9/AlquiiteMain.jpg",
      "galaxy": "Eissentam",
      "glyphs": "000BFA555C31",
      "civilization": "Legacy EisHub",
      "discovered_by": "",
      "discoverer_page": "ElCapoChino",
      "discoverer_url": "https://nmsgalactichub.miraheze.org/wiki/ElCapoChino"
    },
    {
      "page": "Atmanite",
      "page_url": "https://nmsgalactichub.miraheze.org/wiki/Atmanite",
      "name": "Atmanite",
      "image_name": "Atmanite.jpg",
      "image_url": "https://static.wikitide.net/nmsgalactichubwiki/0/05/Atmanite.jpg",
      "galaxy": "Euclid",
      "glyphs": "3051F9556C2F",
      "civilization": "Legacy Galactic Hub",
      "discovered_by": "",
      "discoverer_page": "Donrhowland",
      "discoverer_url": "https://nmsgalactichub.miraheze.org/wiki/Donrhowland"
    },
    {
      "page": "Auskinite",
      "page_url": "https://nmsgalactichub.miraheze.org/wiki/Auskinite",
      "name": "Auskinite",
      "image_name": "Screenshot (5769).png",
      "image_url": "https://static.wikitide.net/nmsgalactichubwiki/4/4b/Screenshot_%285769%29.png",
      "galaxy": "Calypso",
      "glyphs": "1220F9556C2F",
      "civilization": "Galactic Hub Calypso",
      "discovered_by": "",
      "discoverer_page": "Randomner",
      "discoverer_url": "https://nmsgalactichub.miraheze.org/wiki/Randomner"
    },
    {
      "page": "Ayiryneite",
      "page_url": "https://nmsgalactichub.miraheze.org/wiki/Ayiryneite",
      "name": "Ayiryneite",
      "image_name": "Ayir1.jpg",
      "image_url": "https://static.wikitide.net/nmsgalactichubwiki/1/16/Ayir1.jpg",
      "galaxy": "Euclid",
      "glyphs": "1051F9556C2F",
      "civilization": "Legacy Galactic Hub",
      "discovered_by": "",
      "discoverer_page": "Donrhowland",
      "discoverer_url": "https://nmsgalactichub.miraheze.org/wiki/Donrhowland"
    },
    {
      "page": "Aysilite",
      "page_url": "https://nmsgalactichub.miraheze.org/wiki/Aysilite",
      "name": "Aysilite",
      "image_name": "Moonshield_aysilite.png",
      "image_url": "https://nmsgalactichub.miraheze.org/wiki/Special:FilePath/Moonshield_aysilite.png",
      "galaxy": "Euclid",
      "glyphs": "20DDCE58AC1F",
      "civilization": "Galactic Hub Project",
      "discovered_by": "",
      "discoverer_page": "DinoZeppelin",
      "discoverer_url": "https://nmsgalactichub.miraheze.org/wiki/DinoZeppelin"
    },
    {
      "page": "Azanshise",
      "page_url": "https://nmsgalactichub.miraheze.org/wiki/Azanshise",
      "name": "Azanshise",
      "image_name": "Screenshot (5794).png",
      "image_url": "https://static.wikitide.net/nmsgalactichubwiki/0/00/Screenshot_%285794%29.png",
      "galaxy": "Calypso",
      "glyphs": "1220F9556C2F",
      "civilization": "Galactic Hub Calypso",
      "discovered_by": "",
      "discoverer_page": "Randomner",
      "discoverer_url": "https://nmsgalactichub.miraheze.org/wiki/Randomner"
    },
    {
      "page": "Azzeratsite",
      "page_url": "https://nmsgalactichub.miraheze.org/wiki/Azzeratsite",
      "name": "Azzeratsite",
      "image_name": "Screenshot (5134).png",
      "image_url": "https://static.wikitide.net/nmsgalactichubwiki/1/10/Screenshot_%285134%29.png",
      "galaxy": "Calypso",
      "glyphs": "1220F9556C2F",
      "civilization": "Galactic Hub Calypso",
      "discovered_by": "",
      "discoverer_page": "Randomner",
      "discoverer_url": "https://nmsgalactichub.miraheze.org/wiki/Randomner"
    },
    {
      "page": "Bahurammite",
      "page_url": "https://nmsgalactichub.miraheze.org/wiki/Bahurammite",
      "name": "Bahurammite",
      "image_name": "Screenshot (3355).png",
      "image_url": "https://static.wikitide.net/nmsgalactichubwiki/6/6c/Screenshot_%283355%29.png",
      "galaxy": "Calypso",
      "glyphs": "3220F9556C2F",
      "civilization": "Galactic Hub Calypso",
      "discovered_by": "",
      "discoverer_page": "Randomner",
      "discoverer_url": "https://nmsgalactichub.miraheze.org/wiki/Randomner"
    },
    {
      "page": "Bastnaite",
      "page_url": "https://nmsgalactichub.miraheze.org/wiki/Bastnaite",
      "name": "Bastnaite",
      "image_name": "BastnaiteMain.jpg",
      "image_url": "https://static.wikitide.net/nmsgalactichubwiki/7/7e/BastnaiteMain.jpg",
      "galaxy": "Eissentam",
      "glyphs": "000BFA555C31",
      "civilization": "Legacy EisHub",
      "discovered_by": "",
      "discoverer_page": "ElCapoChino",
      "discoverer_url": "https://nmsgalactichub.miraheze.org/wiki/ElCapoChino"
    },
    {
      "page": "Beswurite",
      "page_url": "https://nmsgalactichub.miraheze.org/wiki/Beswurite",
      "name": "Beswurite",
      "image_name": "Besw1.jpg",
      "image_url": "https://static.wikitide.net/nmsgalactichubwiki/b/b2/Besw1.jpg",
      "galaxy": "Euclid",
      "glyphs": "1051F9556C2F",
      "civilization": "Legacy Galactic Hub",
      "discovered_by": "",
      "discoverer_page": "Donrhowland",
      "discoverer_url": "https://nmsgalactichub.miraheze.org/wiki/Donrhowland"
    },
    {
      "page": "Betaniite",
      "page_url": "https://nmsgalactichub.miraheze.org/wiki/Betaniite",
      "name": "Betaniite",
      "image_name": "Screenshot (3365).png",
      "image_url": "https://static.wikitide.net/nmsgalactichubwiki/8/88/Screenshot_%283365%29.png",
      "galaxy": "Calypso",
      "glyphs": "3220F9556C2F",
      "civilization": "Galactic Hub Calypso",
      "discovered_by": "",
      "discoverer_page": "Randomner",
      "discoverer_url": "https://nmsgalactichub.miraheze.org/wiki/Randomner"
    },
    {
      "page": "Bigcrite",
      "page_url": "https://nmsgalactichub.miraheze.org/wiki/Bigcrite",
      "name": "Bigcrite",
      "image_name": "Bigc1.jpg",
      "image_url": "https://static.wikitide.net/nmsgalactichubwiki/9/9d/Bigc1.jpg",
      "galaxy": "Euclid",
      "glyphs": "1051F9556C2F",
      "civilization": "Legacy Galactic Hub",
      "discovered_by": "",
      "discoverer_page": "Donrhowland",
      "discoverer_url": "https://nmsgalactichub.miraheze.org/wiki/Donrhowland"
    },
    {
      "page": "Burosmite",
      "page_url": "https://nmsgalactichub.miraheze.org/wiki/Burosmite",
      "name": "Burosmite",
      "image_name": "Buro1.jpg",
      "image_url": "https://static.wikitide.net/nmsgalactichubwiki/4/4d/Buro1.jpg",
      "galaxy": "Euclid",
      "glyphs": "3051F9556C2F",
      "civilization": "Legacy Galactic Hub",
      "discovered_by": "",
      "discoverer_page": "Donrhowland",
      "discoverer_url": "https://nmsgalactichub.miraheze.org/wiki/Donrhowland"
    },
    {
      "page": "Cobotime",
      "page_url": "https://nmsgalactichub.miraheze.org/wiki/Cobotime",
      "name": "Cobotime",
      "image_name": "efaff808-e768-42f4-83f8-287af36d384f.png",
      "image_url": "https://nmsgalactichub.miraheze.org/wiki/Special:FilePath/efaff808-e768-42f4-83f8-287af36d384f.png",
      "galaxy": "Calypso",
      "glyphs": "2082F9557C30",
      "civilization": "Galactic Hub Calypso",
      "discovered_by": "Wheeler",
      "discoverer_page": "",
      "discoverer_url": ""
    },
    {
      "page": "Dalyaite",
      "page_url": "https://nmsgalactichub.miraheze.org/wiki/Dalyaite",
      "name": "Dalyaite",
      "image_name": "Screenshot (3371).png",
      "image_url": "https://static.wikitide.net/nmsgalactichubwiki/4/45/Screenshot_%283371%29.png",
      "galaxy": "Calypso",
      "glyphs": "3220F9556C2F",
      "civilization": "Galactic Hub Calypso",
      "discovered_by": "",
      "discoverer_page": "Randomner",
      "discoverer_url": "https://nmsgalactichub.miraheze.org/wiki/Randomner"
    },
    {
      "page": "Dilammoite",
      "page_url": "https://nmsgalactichub.miraheze.org/wiki/Dilammoite",
      "name": "Dilammoite",
      "image_name": "DilammoiteMain.jpg",
      "image_url": "https://static.wikitide.net/nmsgalactichubwiki/0/06/DilammoiteMain.jpg",
      "galaxy": "Eissentam",
      "glyphs": "400BFA555C31",
      "civilization": "Legacy EisHub",
      "discovered_by": "",
      "discoverer_page": "ElCapoChino",
      "discoverer_url": "https://nmsgalactichub.miraheze.org/wiki/ElCapoChino"
    },
    {
      "page": "Dileyfiite",
      "page_url": "https://nmsgalactichub.miraheze.org/wiki/Dileyfiite",
      "name": "Dileyfiite",
      "image_name": "DileyfiiteMain.jpg",
      "image_url": "https://static.wikitide.net/nmsgalactichubwiki/1/1b/DileyfiiteMain.jpg",
      "galaxy": "Eissentam",
      "glyphs": "000BFA555C31",
      "civilization": "Legacy EisHub",
      "discovered_by": "",
      "discoverer_page": "ElCapoChino",
      "discoverer_url": "https://nmsgalactichub.miraheze.org/wiki/ElCapoChino"
    },
    {
      "page": "Dolibelite",
      "page_url": "https://nmsgalactichub.miraheze.org/wiki/Dolibelite",
      "name": "Dolibelite",
      "image_name": "Screenshot (3230).png",
      "image_url": "https://static.wikitide.net/nmsgalactichubwiki/e/e3/Screenshot_%283230%29.png",
      "galaxy": "Calypso",
      "glyphs": "2220F9556C2F",
      "civilization": "Galactic Hub Calypso",
      "discovered_by": "",
      "discoverer_page": "Randomner",
      "discoverer_url": "https://nmsgalactichub.miraheze.org/wiki/Randomner"
    },
    {
      "page": "Dwightine",
      "page_url": "https://nmsgalactichub.miraheze.org/wiki/Dwightine",
      "name": "Dwightine",
      "image_name": "DwightineMain.jpg",
      "image_url": "https://static.wikitide.net/nmsgalactichubwiki/3/34/DwightineMain.jpg",
      "galaxy": "Eissentam",
      "glyphs": "000BFA555C31",
      "civilization": "Legacy EisHub",
      "discovered_by": "",
      "discoverer_page": "ElCapoChino",
      "discoverer_url": "https://nmsgalactichub.miraheze.org/wiki/ElCapoChino"
    },
    {
      "page": "Eclasite",
      "page_url": "https://nmsgalactichub.miraheze.org/wiki/Eclasite",
      "name": "Eclasite",
      "image_name": "Screenshot (3390).png",
      "image_url": "https://static.wikitide.net/nmsgalactichubwiki/c/cd/Screenshot_%283390%29.png",
      "galaxy": "Calypso",
      "glyphs": "3220F9556C2F",
      "civilization": "Galactic Hub Calypso",
      "discovered_by": "",
      "discoverer_page": "Randomner",
      "discoverer_url": "https://nmsgalactichub.miraheze.org/wiki/Randomner"
    },
    {
      "page": "Econnaite",
      "page_url": "https://nmsgalactichub.miraheze.org/wiki/Econnaite",
      "name": "Econnaite",
      "image_name": "EconnaiteMain.jpg",
      "image_url": "https://static.wikitide.net/nmsgalactichubwiki/d/d2/EconnaiteMain.jpg",
      "galaxy": "Eissentam",
      "glyphs": "400BFA555C31",
      "civilization": "Legacy EisHub",
      "discovered_by": "",
      "discoverer_page": "ElCapoChino",
      "discoverer_url": "https://nmsgalactichub.miraheze.org/wiki/ElCapoChino"
    },
    {
      "page": "Ederhoite",
      "page_url": "https://nmsgalactichub.miraheze.org/wiki/Ederhoite",
      "name": "Ederhoite",
      "image_name": "Moonshield_ederhoite.png",
      "image_url": "https://nmsgalactichub.miraheze.org/wiki/Special:FilePath/Moonshield_ederhoite.png",
      "galaxy": "Euclid",
      "glyphs": "20DDCE58AC1F",
      "civilization": "Galactic Hub Project",
      "discovered_by": "",
      "discoverer_page": "DinoZeppelin",
      "discoverer_url": "https://nmsgalactichub.miraheze.org/wiki/DinoZeppelin"
    },
    {
      "page": "Eederite",
      "page_url": "https://nmsgalactichub.miraheze.org/wiki/Eederite",
      "name": "Eederite",
      "image_name": "EederiteMain.jpg",
      "image_url": "https://static.wikitide.net/nmsgalactichubwiki/0/01/EederiteMain.jpg",
      "galaxy": "Eissentam",
      "glyphs": "000BFA555C31",
      "civilization": "Legacy EisHub",
      "discovered_by": "",
      "discoverer_page": "ElCapoChino",
      "discoverer_url": "https://nmsgalactichub.miraheze.org/wiki/ElCapoChino"
    },
    {
      "page": "Eimerite",
      "page_url": "https://nmsgalactichub.miraheze.org/wiki/Eimerite",
      "name": "Eimerite",
      "image_name": "EimeriteMain.jpg",
      "image_url": "https://static.wikitide.net/nmsgalactichubwiki/5/5a/EimeriteMain.jpg",
      "galaxy": "Eissentam",
      "glyphs": "200BFA555C31",
      "civilization": "Legacy EisHub",
      "discovered_by": "",
      "discoverer_page": "ElCapoChino",
      "discoverer_url": "https://nmsgalactichub.miraheze.org/wiki/ElCapoChino"
    },
    {
      "page": "Eirinekite",
      "page_url": "https://nmsgalactichub.miraheze.org/wiki/Eirinekite",
      "name": "Eirinekite",
      "image_name": "Eirinekite.png",
      "image_url": "https://static.wikitide.net/nmsgalactichubwiki/9/9d/Eirinekite.png",
      "galaxy": "Eissentam",
      "glyphs": "405609555D30",
      "civilization": "Galactic Hub Eissentam",
      "discovered_by": "[[User:Tjawsome7305|A random Typewriter]]",
      "discoverer_page": "",
      "discoverer_url": ""
    },
    {
      "page": "Enbacite",
      "page_url": "https://nmsgalactichub.miraheze.org/wiki/Enbacite",
      "name": "Enbacite",
      "image_name": "EnbaciteMain.jpg",
      "image_url": "https://static.wikitide.net/nmsgalactichubwiki/0/0f/EnbaciteMain.jpg",
      "galaxy": "Eissentam",
      "glyphs": "200BFA555C31",
      "civilization": "Legacy EisHub",
      "discovered_by": "",
      "discoverer_page": "ElCapoChino",
      "discoverer_url": "https://nmsgalactichub.miraheze.org/wiki/ElCapoChino"
    },
    {
      "page": "Ervansite",
      "page_url": "https://nmsgalactichub.miraheze.org/wiki/Ervansite",
      "name": "Ervansite",
      "image_name": "Screenshot (3255).png",
      "image_url": "https://static.wikitide.net/nmsgalactichubwiki/2/2b/Screenshot_%283255%29.png",
      "galaxy": "Calypso",
      "glyphs": "2220F9556C2F",
      "civilization": "Galactic Hub Calypso",
      "discovered_by": "",
      "discoverer_page": "Randomner",
      "discoverer_url": "https://nmsgalactichub.miraheze.org/wiki/Randomner"
    },
    {
      "page": "Fobolite",
      "page_url": "https://nmsgalactichub.miraheze.org/wiki/Fobolite",
      "name": "Fobolite",
      "image_name": "Fobo1.jpg",
      "image_url": "https://static.wikitide.net/nmsgalactichubwiki/a/a2/Fobo1.jpg",
      "galaxy": "Euclid",
      "glyphs": "3051F9556C2F",
      "civilization": "Legacy Galactic Hub",
      "discovered_by": "",
      "discoverer_page": "Donrhowland",
      "discoverer_url": "https://nmsgalactichub.miraheze.org/wiki/Donrhowland"
    },
    {
      "page": "Gearsite",
      "page_url": "https://nmsgalactichub.miraheze.org/wiki/Gearsite",
      "name": "Gearsite",
      "image_name": "Gear1.jpg",
      "image_url": "https://static.wikitide.net/nmsgalactichubwiki/0/0d/Gear1.jpg",
      "galaxy": "Euclid",
      "glyphs": "3051F9556C2F",
      "civilization": "Legacy Galactic Hub",
      "discovered_by": "",
      "discoverer_page": "Donrhowland",
      "discoverer_url": "https://nmsgalactichub.miraheze.org/wiki/Donrhowland"
    },
    {
      "page": "Georgeerite",
      "page_url": "https://nmsgalactichub.miraheze.org/wiki/Georgeerite",
      "name": "Georgeerite",
      "image_name": "GeorgeeriteMain.jpg",
      "image_url": "https://static.wikitide.net/nmsgalactichubwiki/1/19/GeorgeeriteMain.jpg",
      "galaxy": "Eissentam",
      "glyphs": "400BFA555C31",
      "civilization": "Legacy EisHub",
      "discovered_by": "",
      "discoverer_page": "ElCapoChino",
      "discoverer_url": "https://nmsgalactichub.miraheze.org/wiki/ElCapoChino"
    },
    {
      "page": "Gezzoite",
      "page_url": "https://nmsgalactichub.miraheze.org/wiki/Gezzoite",
      "name": "Gezzoite",
      "image_name": "GezzoiteMain.jpg",
      "image_url": "https://static.wikitide.net/nmsgalactichubwiki/6/61/GezzoiteMain.jpg",
      "galaxy": "Eissentam",
      "glyphs": "200BFA555C31",
      "civilization": "Legacy EisHub",
      "discovered_by": "",
      "discoverer_page": "ElCapoChino",
      "discoverer_url": "https://nmsgalactichub.miraheze.org/wiki/ElCapoChino"
    },
    {
      "page": "Giadeite",
      "page_url": "https://nmsgalactichub.miraheze.org/wiki/Giadeite",
      "name": "Giadeite",
      "image_name": "gia20250503105824_1.jpg",
      "image_url": "https://nmsgalactichub.miraheze.org/wiki/Special:FilePath/gia20250503105824_1.jpg",
      "galaxy": "Euclid",
      "glyphs": "5429CF58AC1F",
      "civilization": "Galactic Hub Project",
      "discovered_by": "",
      "discoverer_page": "lazybud",
      "discoverer_url": "https://nmsgalactichub.miraheze.org/wiki/lazybud"
    },
    {
      "page": "Granoite",
      "page_url": "https://nmsgalactichub.miraheze.org/wiki/Granoite",
      "name": "Granoite",
      "image_name": "GranoiteMain.jpg",
      "image_url": "https://static.wikitide.net/nmsgalactichubwiki/8/83/GranoiteMain.jpg",
      "galaxy": "Eissentam",
      "glyphs": "200BFA555C31",
      "civilization": "Legacy EisHub",
      "discovered_by": "",
      "discoverer_page": "ElCapoChino",
      "discoverer_url": "https://nmsgalactichub.miraheze.org/wiki/ElCapoChino"
    },
    {
      "page": "Grouaite",
      "page_url": "https://nmsgalactichub.miraheze.org/wiki/Grouaite",
      "name": "Grouaite",
      "image_name": "Screenshot (3209).png",
      "image_url": "https://static.wikitide.net/nmsgalactichubwiki/3/33/Screenshot_%283209%29.png",
      "galaxy": "Calypso",
      "glyphs": "2220F9556C2F",
      "civilization": "Galactic Hub Calypso",
      "discovered_by": "",
      "discoverer_page": "Randomner",
      "discoverer_url": "https://nmsgalactichub.miraheze.org/wiki/Randomner"
    },
    {
      "page": "Guidotine",
      "page_url": "https://nmsgalactichub.miraheze.org/wiki/Guidotine",
      "name": "Guidotine",
      "image_name": "Screenshot (3258).png",
      "image_url": "https://static.wikitide.net/nmsgalactichubwiki/3/31/Screenshot_%283258%29.png",
      "galaxy": "Calypso",
      "glyphs": "2220F9556C2F",
      "civilization": "Galactic Hub Calypso",
      "discovered_by": "",
      "discoverer_page": "Randomner",
      "discoverer_url": "https://nmsgalactichub.miraheze.org/wiki/Randomner"
    },
    {
      "page": "Gwornwalite",
      "page_url": "https://nmsgalactichub.miraheze.org/wiki/Gwornwalite",
      "name": "Gwornwalite",
      "image_name": "Gwor1.jpg",
      "image_url": "https://static.wikitide.net/nmsgalactichubwiki/6/64/Gwor1.jpg",
      "galaxy": "Euclid",
      "glyphs": "1051F9556C2F",
      "civilization": "Legacy Galactic Hub",
      "discovered_by": "",
      "discoverer_page": "Donrhowland",
      "discoverer_url": "https://nmsgalactichub.miraheze.org/wiki/Donrhowland"
    },
    {
      "page": "Hammeite",
      "page_url": "https://nmsgalactichub.miraheze.org/wiki/Hammeite",
      "name": "Hammeite",
      "image_name": "HammeiteMain.jpg",
      "image_url": "https://static.wikitide.net/nmsgalactichubwiki/a/a4/HammeiteMain.jpg",
      "galaxy": "Eissentam",
      "glyphs": "200BFA555C31",
      "civilization": "Legacy EisHub",
      "discovered_by": "",
      "discoverer_page": "ElCapoChino",
      "discoverer_url": "https://nmsgalactichub.miraheze.org/wiki/ElCapoChino"
    },
    {
      "page": "Heninnite",
      "page_url": "https://nmsgalactichub.miraheze.org/wiki/Heninnite",
      "name": "Heninnite",
      "image_name": "HeninniteMain.jpg",
      "image_url": "https://static.wikitide.net/nmsgalactichubwiki/4/46/HeninniteMain.jpg",
      "galaxy": "Eissentam",
      "glyphs": "000BFA555C31",
      "civilization": "Legacy EisHub",
      "discovered_by": "",
      "discoverer_page": "ElCapoChino",
      "discoverer_url": "https://nmsgalactichub.miraheze.org/wiki/ElCapoChino"
    },
    {
      "page": "Hereallaite",
      "page_url": "https://nmsgalactichub.miraheze.org/wiki/Hereallaite",
      "name": "Hereallaite",
      "image_name": "Here1.jpg",
      "image_url": "https://static.wikitide.net/nmsgalactichubwiki/2/21/Here1.jpg",
      "galaxy": "Euclid",
      "glyphs": "1051F9556C2F",
      "civilization": "Legacy Galactic Hub",
      "discovered_by": "",
      "discoverer_page": "Donrhowland",
      "discoverer_url": "https://nmsgalactichub.miraheze.org/wiki/Donrhowland"
    },
    {
      "page": "Icenniite",
      "page_url": "https://nmsgalactichub.miraheze.org/wiki/Icenniite",
      "name": "Icenniite",
      "image_name": "IcenniiteMain.jpg",
      "image_url": "https://static.wikitide.net/nmsgalactichubwiki/5/50/IcenniiteMain.jpg",
      "galaxy": "Eissentam",
      "glyphs": "400BFA555C31",
      "civilization": "Legacy EisHub",
      "discovered_by": "",
      "discoverer_page": "ElCapoChino",
      "discoverer_url": "https://nmsgalactichub.miraheze.org/wiki/ElCapoChino"
    },
    {
      "page": "Icgedriite",
      "page_url": "https://nmsgalactichub.miraheze.org/wiki/Icgedriite",
      "name": "Icgedriite",
      "image_name": "Icgedriite.jpg",
      "image_url": "https://static.wikitide.net/nmsgalactichubwiki/0/0d/Icgedriite.jpg",
      "galaxy": "Euclid",
      "glyphs": "3051F9556C2F",
      "civilization": "Legacy Galactic Hub",
      "discovered_by": "",
      "discoverer_page": "Donrhowland",
      "discoverer_url": "https://nmsgalactichub.miraheze.org/wiki/Donrhowland"
    },
    {
      "page": "Icoanite",
      "page_url": "https://nmsgalactichub.miraheze.org/wiki/Icoanite",
      "name": "Icoanite",
      "image_name": "Icoa1.jpg",
      "image_url": "https://static.wikitide.net/nmsgalactichubwiki/1/10/Icoa1.jpg",
      "galaxy": "Euclid",
      "glyphs": "3051F9556C2F",
      "civilization": "Legacy Galactic Hub",
      "discovered_by": "",
      "discoverer_page": "Donrhowland",
      "discoverer_url": "https://nmsgalactichub.miraheze.org/wiki/Donrhowland"
    },
    {
      "page": "Imzeyite",
      "page_url": "https://nmsgalactichub.miraheze.org/wiki/Imzeyite",
      "name": "Imzeyite",
      "image_name": "ImzeyiteMain.jpg",
      "image_url": "https://static.wikitide.net/nmsgalactichubwiki/1/15/ImzeyiteMain.jpg",
      "galaxy": "Eissentam",
      "glyphs": "200BFA555C31",
      "civilization": "Legacy EisHub",
      "discovered_by": "",
      "discoverer_page": "ElCapoChino",
      "discoverer_url": "https://nmsgalactichub.miraheze.org/wiki/ElCapoChino"
    },
    {
      "page": "Iopeartibe",
      "page_url": "https://nmsgalactichub.miraheze.org/wiki/Iopeartibe",
      "name": "Iopeartibe",
      "image_name": "Screenshot (5133).png",
      "image_url": "https://static.wikitide.net/nmsgalactichubwiki/6/64/Screenshot_%285133%29.png",
      "galaxy": "Calypso",
      "glyphs": "1220F9556C2F",
      "civilization": "Galactic Hub Calypso",
      "discovered_by": "",
      "discoverer_page": "Randomner",
      "discoverer_url": "https://nmsgalactichub.miraheze.org/wiki/Randomner"
    },
    {
      "page": "Irksutibe",
      "page_url": "https://nmsgalactichub.miraheze.org/wiki/Irksutibe",
      "name": "Irksutibe",
      "image_name": "IrksutibeMain.jpg",
      "image_url": "https://static.wikitide.net/nmsgalactichubwiki/4/43/IrksutibeMain.jpg",
      "galaxy": "Eissentam",
      "glyphs": "200BFA555C31",
      "civilization": "Legacy EisHub",
      "discovered_by": "",
      "discoverer_page": "ElCapoChino",
      "discoverer_url": "https://nmsgalactichub.miraheze.org/wiki/ElCapoChino"
    },
    {
      "page": "Jasmuite",
      "page_url": "https://nmsgalactichub.miraheze.org/wiki/Jasmuite",
      "name": "Jasmuite",
      "image_name": "Screenshot (3247).png",
      "image_url": "https://static.wikitide.net/nmsgalactichubwiki/5/55/Screenshot_%283247%29.png",
      "galaxy": "Calypso",
      "glyphs": "2220F9556C2F",
      "civilization": "Galactic Hub Calypso",
      "discovered_by": "",
      "discoverer_page": "Randomner",
      "discoverer_url": "https://nmsgalactichub.miraheze.org/wiki/Randomner"
    },
    {
      "page": "Jimthite",
      "page_url": "https://nmsgalactichub.miraheze.org/wiki/Jimthite",
      "name": "Jimthite",
      "image_name": "JimtB1.jpg",
      "image_url": "https://static.wikitide.net/nmsgalactichubwiki/e/e9/JimtB1.jpg",
      "galaxy": "Euclid",
      "glyphs": "1051F9556C2F",
      "civilization": "Legacy Galactic Hub",
      "discovered_by": "",
      "discoverer_page": "Donrhowland",
      "discoverer_url": "https://nmsgalactichub.miraheze.org/wiki/Donrhowland"
    },
    {
      "page": "Josepiite",
      "page_url": "https://nmsgalactichub.miraheze.org/wiki/Josepiite",
      "name": "Josepiite",
      "image_name": "Screenshot (3210).png",
      "image_url": "https://static.wikitide.net/nmsgalactichubwiki/3/3d/Screenshot_%283210%29.png",
      "galaxy": "Calypso",
      "glyphs": "2220F9556C2F",
      "civilization": "Galactic Hub Calypso",
      "discovered_by": "",
      "discoverer_page": "Randomner",
      "discoverer_url": "https://nmsgalactichub.miraheze.org/wiki/Randomner"
    },
    {
      "page": "Kettroite",
      "page_url": "https://nmsgalactichub.miraheze.org/wiki/Kettroite",
      "name": "Kettroite",
      "image_name": "KettroiteMain.jpg",
      "image_url": "https://static.wikitide.net/nmsgalactichubwiki/2/23/KettroiteMain.jpg",
      "galaxy": "Eissentam",
      "glyphs": "000BFA555C31",
      "civilization": "Legacy EisHub",
      "discovered_by": "",
      "discoverer_page": "ElCapoChino",
      "discoverer_url": "https://nmsgalactichub.miraheze.org/wiki/ElCapoChino"
    },
    {
      "page": "Kilindeite",
      "page_url": "https://nmsgalactichub.miraheze.org/wiki/Kilindeite",
      "name": "Kilindeite",
      "image_name": "75795ac6-bbc9-4193-b3c5-6ef8143a7296.png",
      "image_url": "https://static.wikitide.net/nmsgalactichubwiki/f/ff/75795ac6-bbc9-4193-b3c5-6ef8143a7296.png",
      "galaxy": "Calypso",
      "glyphs": "2082F9557C30",
      "civilization": "Galactic Hub Calypso",
      "discovered_by": "",
      "discoverer_page": "Dovahren",
      "discoverer_url": "https://nmsgalactichub.miraheze.org/wiki/Dovahren"
    },
    {
      "page": "Kombeite",
      "page_url": "https://nmsgalactichub.miraheze.org/wiki/Kombeite",
      "name": "Kombeite",
      "image_name": "Komb1.jpg",
      "image_url": "https://static.wikitide.net/nmsgalactichubwiki/7/77/Komb1.jpg",
      "galaxy": "Euclid",
      "glyphs": "2051F9556C2F",
      "civilization": "Legacy Galactic Hub",
      "discovered_by": "",
      "discoverer_page": "Donrhowland",
      "discoverer_url": "https://nmsgalactichub.miraheze.org/wiki/Donrhowland"
    },
    {
      "page": "Lacandite",
      "page_url": "https://nmsgalactichub.miraheze.org/wiki/Lacandite",
      "name": "Lacandite",
      "image_name": "Screenshot (3379).png",
      "image_url": "https://static.wikitide.net/nmsgalactichubwiki/e/e2/Screenshot_%283379%29.png",
      "galaxy": "Calypso",
      "glyphs": "3220F9556C2F",
      "civilization": "Galactic Hub Calypso",
      "discovered_by": "",
      "discoverer_page": "Randomner",
      "discoverer_url": "https://nmsgalactichub.miraheze.org/wiki/Randomner"
    },
    {
      "page": "Lavamelon (Gahdanoite)",
      "page_url": "https://nmsgalactichub.miraheze.org/wiki/Lavamelon_(Gahdanoite)",
      "name": "Lavamelon (Gahdanoite)",
      "image_name": "Lavamelon.png",
      "image_url": "https://static.wikitide.net/nmsgalactichubwiki/6/6e/Lavamelon.png",
      "galaxy": "Eissentam",
      "glyphs": "607F09555D30",
      "civilization": "Galactic Hub Eissentam",
      "discovered_by": "[[User:Tjawsome7305|A random Typewriter]]",
      "discoverer_page": "",
      "discoverer_url": ""
    },
    {
      "page": "Liberlite",
      "page_url": "https://nmsgalactichub.miraheze.org/wiki/Liberlite",
      "name": "Liberlite",
      "image_name": "Liber1.jpg",
      "image_url": "https://static.wikitide.net/nmsgalactichubwiki/2/2a/Liber1.jpg",
      "galaxy": "Euclid",
      "glyphs": "3051F9556C2F",
      "civilization": "Legacy Galactic Hub",
      "discovered_by": "",
      "discoverer_page": "Donrhowland",
      "discoverer_url": "https://nmsgalactichub.miraheze.org/wiki/Donrhowland"
    },
    {
      "page": "Lidgeite",
      "page_url": "https://nmsgalactichub.miraheze.org/wiki/Lidgeite",
      "name": "Lidgeite",
      "image_name": "Screenshot (5789).png",
      "image_url": "https://static.wikitide.net/nmsgalactichubwiki/d/d5/Screenshot_%285789%29.png",
      "galaxy": "Calypso",
      "glyphs": "1220F9556C2F",
      "civilization": "Galactic Hub Calypso",
      "discovered_by": "",
      "discoverer_page": "Randomner",
      "discoverer_url": "https://nmsgalactichub.miraheze.org/wiki/Randomner"
    },
    {
      "page": "Limounaite",
      "page_url": "https://nmsgalactichub.miraheze.org/wiki/Limounaite",
      "name": "Limounaite",
      "image_name": "Limo1.jpg",
      "image_url": "https://static.wikitide.net/nmsgalactichubwiki/4/48/Limo1.jpg",
      "galaxy": "Euclid",
      "glyphs": "1051F9556C2F",
      "civilization": "Legacy Galactic Hub",
      "discovered_by": "",
      "discoverer_page": "Donrhowland",
      "discoverer_url": "https://nmsgalactichub.miraheze.org/wiki/Donrhowland"
    },
    {
      "page": "Lukanovaite",
      "page_url": "https://nmsgalactichub.miraheze.org/wiki/Lukanovaite",
      "name": "Lukanovaite",
      "image_name": "6a71ad8b-ca92-42b4-b521-2e5c294535dc.png",
      "image_url": "https://static.wikitide.net/nmsgalactichubwiki/e/e6/6a71ad8b-ca92-42b4-b521-2e5c294535dc.png",
      "galaxy": "Euclid",
      "glyphs": "6078D058AC1D",
      "civilization": "Galactic Hub Project",
      "discovered_by": "1/12/2026",
      "discoverer_page": "Dr. Cassiopeia",
      "discoverer_url": "https://nmsgalactichub.miraheze.org/wiki/Dr._Cassiopeia"
    },
    {
      "page": "Luynsakiite",
      "page_url": "https://nmsgalactichub.miraheze.org/wiki/Luynsakiite",
      "name": "Luynsakiite",
      "image_name": "Luynsakiite.jpg",
      "image_url": "https://static.wikitide.net/nmsgalactichubwiki/8/87/Luynsakiite.jpg",
      "galaxy": "Eissentam",
      "glyphs": "60E1FA555C2F",
      "civilization": "Legacy EisHub",
      "discovered_by": "[https://www.reddit.com/user/Lenni009 Lenni]",
      "discoverer_page": "",
      "discoverer_url": ""
    },
    {
      "page": "Mahnsite",
      "page_url": "https://nmsgalactichub.miraheze.org/wiki/Mahnsite",
      "name": "Mahnsite",
      "image_name": "MahnsiteMain.jpg",
      "image_url": "https://static.wikitide.net/nmsgalactichubwiki/7/72/MahnsiteMain.jpg",
      "galaxy": "Eissentam",
      "glyphs": "000BFA555C31",
      "civilization": "Legacy EisHub",
      "discovered_by": "",
      "discoverer_page": "ElCapoChino",
      "discoverer_url": "https://nmsgalactichub.miraheze.org/wiki/ElCapoChino"
    },
    {
      "page": "Mopundhite",
      "page_url": "https://nmsgalactichub.miraheze.org/wiki/Mopundhite",
      "name": "Mopundhite",
      "image_name": "Screenshot (010).png",
      "image_url": "https://static.wikitide.net/nmsgalactichubwiki/d/d7/Screenshot_%28010%29.png",
      "galaxy": "Calypso",
      "glyphs": "2220F9556C2F",
      "civilization": "Galactic Hub Calypso",
      "discovered_by": "",
      "discoverer_page": "Randomner",
      "discoverer_url": "https://nmsgalactichub.miraheze.org/wiki/Randomner"
    },
    {
      "page": "Nakingite",
      "page_url": "https://nmsgalactichub.miraheze.org/wiki/Nakingite",
      "name": "Nakingite",
      "image_name": "NakingiteMain.jpg",
      "image_url": "https://static.wikitide.net/nmsgalactichubwiki/5/52/NakingiteMain.jpg",
      "galaxy": "Eissentam",
      "glyphs": "400BFA555C31",
      "civilization": "Legacy EisHub",
      "discovered_by": "",
      "discoverer_page": "ElCapoChino",
      "discoverer_url": "https://nmsgalactichub.miraheze.org/wiki/ElCapoChino"
    },
    {
      "page": "Nanwalkhite",
      "page_url": "https://nmsgalactichub.miraheze.org/wiki/Nanwalkhite",
      "name": "Nanwalkhite",
      "image_name": "NanwalkhiteMain.jpg",
      "image_url": "https://static.wikitide.net/nmsgalactichubwiki/e/e8/NanwalkhiteMain.jpg",
      "galaxy": "Eissentam",
      "glyphs": "200BFA555C31",
      "civilization": "Legacy EisHub",
      "discovered_by": "",
      "discoverer_page": "ElCapoChino",
      "discoverer_url": "https://nmsgalactichub.miraheze.org/wiki/ElCapoChino"
    },
    {
      "page": "Nayuincite",
      "page_url": "https://nmsgalactichub.miraheze.org/wiki/Nayuincite",
      "name": "Nayuincite",
      "image_name": "NayuinciteMain.jpg",
      "image_url": "https://static.wikitide.net/nmsgalactichubwiki/2/24/NayuinciteMain.jpg",
      "galaxy": "Eissentam",
      "glyphs": "000BFA555C31",
      "civilization": "Legacy EisHub",
      "discovered_by": "",
      "discoverer_page": "ElCapoChino",
      "discoverer_url": "https://nmsgalactichub.miraheze.org/wiki/ElCapoChino"
    },
    {
      "page": "Nemaruaiite",
      "page_url": "https://nmsgalactichub.miraheze.org/wiki/Nemaruaiite",
      "name": "Nemaruaiite",
      "image_name": "Nema1.jpg",
      "image_url": "https://static.wikitide.net/nmsgalactichubwiki/6/69/Nema1.jpg",
      "galaxy": "Euclid",
      "glyphs": "1051F9556C2F",
      "civilization": "Legacy Galactic Hub",
      "discovered_by": "",
      "discoverer_page": "Donrhowland",
      "discoverer_url": "https://nmsgalactichub.miraheze.org/wiki/Donrhowland"
    },
    {
      "page": "Nizzaite",
      "page_url": "https://nmsgalactichub.miraheze.org/wiki/Nizzaite",
      "name": "Nizzaite",
      "image_name": "Screenshot (3216).png",
      "image_url": "https://static.wikitide.net/nmsgalactichubwiki/4/4f/Screenshot_%283216%29.png",
      "galaxy": "Calypso",
      "glyphs": "2220F9556C2F",
      "civilization": "Galactic Hub Calypso",
      "discovered_by": "",
      "discoverer_page": "Randomner",
      "discoverer_url": "https://nmsgalactichub.miraheze.org/wiki/Randomner"
    },
    {
      "page": "Noborcite",
      "page_url": "https://nmsgalactichub.miraheze.org/wiki/Noborcite",
      "name": "Noborcite",
      "image_name": "Nobo1.jpg",
      "image_url": "https://static.wikitide.net/nmsgalactichubwiki/b/b2/Nobo1.jpg",
      "galaxy": "Euclid",
      "glyphs": "2051F9556C2F",
      "civilization": "Legacy Galactic Hub",
      "discovered_by": "",
      "discoverer_page": "Donrhowland",
      "discoverer_url": "https://nmsgalactichub.miraheze.org/wiki/Donrhowland"
    },
    {
      "page": "Onbauerite",
      "page_url": "https://nmsgalactichub.miraheze.org/wiki/Onbauerite",
      "name": "Onbauerite",
      "image_name": "OnbaueriteMain.jpg",
      "image_url": "https://static.wikitide.net/nmsgalactichubwiki/3/30/OnbaueriteMain.jpg",
      "galaxy": "Eissentam",
      "glyphs": "400BFA555C31",
      "civilization": "Legacy EisHub",
      "discovered_by": "",
      "discoverer_page": "ElCapoChino",
      "discoverer_url": "https://nmsgalactichub.miraheze.org/wiki/ElCapoChino"
    },
    {
      "page": "Orennite",
      "page_url": "https://nmsgalactichub.miraheze.org/wiki/Orennite",
      "name": "Orennite",
      "image_name": "OrenniteMain.jpg",
      "image_url": "https://static.wikitide.net/nmsgalactichubwiki/2/2e/OrenniteMain.jpg",
      "galaxy": "Eissentam",
      "glyphs": "400BFA555C31",
      "civilization": "Legacy EisHub",
      "discovered_by": "",
      "discoverer_page": "ElCapoChino",
      "discoverer_url": "https://nmsgalactichub.miraheze.org/wiki/ElCapoChino"
    },
    {
      "page": "Osnjamite",
      "page_url": "https://nmsgalactichub.miraheze.org/wiki/Osnjamite",
      "name": "Osnjamite",
      "image_name": "Screenshot (3376).png",
      "image_url": "https://static.wikitide.net/nmsgalactichubwiki/9/96/Screenshot_%283376%29.png",
      "galaxy": "Calypso",
      "glyphs": "3220F9556C2F",
      "civilization": "Galactic Hub Calypso",
      "discovered_by": "",
      "discoverer_page": "Randomner",
      "discoverer_url": "https://nmsgalactichub.miraheze.org/wiki/Randomner"
    },
    {
      "page": "Otilpite",
      "page_url": "https://nmsgalactichub.miraheze.org/wiki/Otilpite",
      "name": "Otilpite",
      "image_name": "Screenshot (3242).png",
      "image_url": "https://static.wikitide.net/nmsgalactichubwiki/b/be/Screenshot_%283242%29.png",
      "galaxy": "Calypso",
      "glyphs": "2220F9556C2F",
      "civilization": "Galactic Hub Calypso",
      "discovered_by": "",
      "discoverer_page": "Randomner",
      "discoverer_url": "https://nmsgalactichub.miraheze.org/wiki/Randomner"
    },
    {
      "page": "Pellesite",
      "page_url": "https://nmsgalactichub.miraheze.org/wiki/Pellesite",
      "name": "Pellesite",
      "image_name": "Pell1.jpg",
      "image_url": "https://static.wikitide.net/nmsgalactichubwiki/9/9a/Pell1.jpg",
      "galaxy": "Euclid",
      "glyphs": "1051F9556C2F",
      "civilization": "Legacy Galactic Hub",
      "discovered_by": "",
      "discoverer_page": "Donrhowland",
      "discoverer_url": "https://nmsgalactichub.miraheze.org/wiki/Donrhowland"
    },
    {
      "page": "Pidialite",
      "page_url": "https://nmsgalactichub.miraheze.org/wiki/Pidialite",
      "name": "Pidialite",
      "image_name": "PidialiteMain.jpg",
      "image_url": "https://static.wikitide.net/nmsgalactichubwiki/c/c6/PidialiteMain.jpg",
      "galaxy": "Eissentam",
      "glyphs": "400BFA555C31",
      "civilization": "Legacy EisHub",
      "discovered_by": "",
      "discoverer_page": "ElCapoChino",
      "discoverer_url": "https://nmsgalactichub.miraheze.org/wiki/ElCapoChino"
    },
    {
      "page": "Pisumokite",
      "page_url": "https://nmsgalactichub.miraheze.org/wiki/Pisumokite",
      "name": "Pisumokite",
      "image_name": "PisumokiteMain.jpg",
      "image_url": "https://static.wikitide.net/nmsgalactichubwiki/c/c5/PisumokiteMain.jpg",
      "galaxy": "Eissentam",
      "glyphs": "400BFA555C31",
      "civilization": "Legacy EisHub",
      "discovered_by": "",
      "discoverer_page": "ElCapoChino",
      "discoverer_url": "https://nmsgalactichub.miraheze.org/wiki/ElCapoChino"
    },
    {
      "page": "Piyrinkite",
      "page_url": "https://nmsgalactichub.miraheze.org/wiki/Piyrinkite",
      "name": "Piyrinkite",
      "image_name": "Screenshot (5765).png",
      "image_url": "https://static.wikitide.net/nmsgalactichubwiki/7/7f/Screenshot_%285765%29.png",
      "galaxy": "Calypso",
      "glyphs": "1220F9556C2F",
      "civilization": "Galactic Hub Calypso",
      "discovered_by": "",
      "discoverer_page": "Randomner",
      "discoverer_url": "https://nmsgalactichub.miraheze.org/wiki/Randomner"
    },
    {
      "page": "Pohthieite",
      "page_url": "https://nmsgalactichub.miraheze.org/wiki/Pohthieite",
      "name": "Pohthieite",
      "image_name": "Poht1.jpg",
      "image_url": "https://static.wikitide.net/nmsgalactichubwiki/e/e0/Poht1.jpg",
      "galaxy": "Euclid",
      "glyphs": "1051F9556C2F",
      "civilization": "Legacy Galactic Hub",
      "discovered_by": "",
      "discoverer_page": "Donrhowland",
      "discoverer_url": "https://nmsgalactichub.miraheze.org/wiki/Donrhowland"
    },
    {
      "page": "Pumangite",
      "page_url": "https://nmsgalactichub.miraheze.org/wiki/Pumangite",
      "name": "Pumangite",
      "image_name": "PumangiteMain.jpg",
      "image_url": "https://static.wikitide.net/nmsgalactichubwiki/e/e9/PumangiteMain.jpg",
      "galaxy": "Eissentam",
      "glyphs": "200BFA555C31",
      "civilization": "Legacy EisHub",
      "discovered_by": "",
      "discoverer_page": "ElCapoChino",
      "discoverer_url": "https://nmsgalactichub.miraheze.org/wiki/ElCapoChino"
    },
    {
      "page": "Rahohnite",
      "page_url": "https://nmsgalactichub.miraheze.org/wiki/Rahohnite",
      "name": "Rahohnite",
      "image_name": "Raho1.jpg",
      "image_url": "https://static.wikitide.net/nmsgalactichubwiki/8/84/Raho1.jpg",
      "galaxy": "Euclid",
      "glyphs": "1051F9556C2F",
      "civilization": "Legacy Galactic Hub",
      "discovered_by": "",
      "discoverer_page": "Donrhowland",
      "discoverer_url": "https://nmsgalactichub.miraheze.org/wiki/Donrhowland"
    },
    {
      "page": "Rakeriite",
      "page_url": "https://nmsgalactichub.miraheze.org/wiki/Rakeriite",
      "name": "Rakeriite",
      "image_name": "Screenshot (5799).png",
      "image_url": "https://static.wikitide.net/nmsgalactichubwiki/1/19/Screenshot_%285799%29.png",
      "galaxy": "Calypso",
      "glyphs": "1220F9556C2F",
      "civilization": "Galactic Hub Calypso",
      "discovered_by": "",
      "discoverer_page": "Randomner",
      "discoverer_url": "https://nmsgalactichub.miraheze.org/wiki/Randomner"
    },
    {
      "page": "Rarebirite",
      "page_url": "https://nmsgalactichub.miraheze.org/wiki/Rarebirite",
      "name": "Rarebirite",
      "image_name": "Rare1.jpg",
      "image_url": "https://static.wikitide.net/nmsgalactichubwiki/6/62/Rare1.jpg",
      "galaxy": "Euclid",
      "glyphs": "2051F9556C2F",
      "civilization": "Legacy Galactic Hub",
      "discovered_by": "",
      "discoverer_page": "Donrhowland",
      "discoverer_url": "https://nmsgalactichub.miraheze.org/wiki/Donrhowland"
    },
    {
      "page": "Rargasite",
      "page_url": "https://nmsgalactichub.miraheze.org/wiki/Rargasite",
      "name": "Rargasite",
      "image_name": "RargasiteMain.jpg",
      "image_url": "https://static.wikitide.net/nmsgalactichubwiki/b/ba/RargasiteMain.jpg",
      "galaxy": "Eissentam",
      "glyphs": "200BFA555C31",
      "civilization": "Legacy EisHub",
      "discovered_by": "",
      "discoverer_page": "ElCapoChino",
      "discoverer_url": "https://nmsgalactichub.miraheze.org/wiki/ElCapoChino"
    },
    {
      "page": "Rinubitanite",
      "page_url": "https://nmsgalactichub.miraheze.org/wiki/Rinubitanite",
      "name": "Rinubitanite",
      "image_name": "Screenshot-1merged.png",
      "image_url": "https://static.wikitide.net/nmsgalactichubwiki/b/b3/Screenshot-1merged.png",
      "galaxy": "Calypso",
      "glyphs": "3220F9556C2F",
      "civilization": "Galactic Hub Calypso",
      "discovered_by": "",
      "discoverer_page": "Randomner",
      "discoverer_url": "https://nmsgalactichub.miraheze.org/wiki/Randomner"
    },
    {
      "page": "Rovskyrite",
      "page_url": "https://nmsgalactichub.miraheze.org/wiki/Rovskyrite",
      "name": "Rovskyrite",
      "image_name": "ba01e32c-ca65-4920-968e-0a789932b226.png",
      "image_url": "https://nmsgalactichub.miraheze.org/wiki/Special:FilePath/ba01e32c-ca65-4920-968e-0a789932b226.png",
      "galaxy": "Calypso",
      "glyphs": "2082F9557C30",
      "civilization": "Galactic Hub Calypso",
      "discovered_by": "",
      "discoverer_page": "Dovahren",
      "discoverer_url": "https://nmsgalactichub.miraheze.org/wiki/Dovahren"
    },
    {
      "page": "Sicideite",
      "page_url": "https://nmsgalactichub.miraheze.org/wiki/Sicideite",
      "name": "Sicideite",
      "image_name": "Screenshot (3226).png",
      "image_url": "https://static.wikitide.net/nmsgalactichubwiki/9/90/Screenshot_%283226%29.png",
      "galaxy": "Calypso",
      "glyphs": "2220F9556C2F",
      "civilization": "Galactic Hub Calypso",
      "discovered_by": "",
      "discoverer_page": "Randomner",
      "discoverer_url": "https://nmsgalactichub.miraheze.org/wiki/Randomner"
    },
    {
      "page": "Soborite",
      "page_url": "https://nmsgalactichub.miraheze.org/wiki/Soborite",
      "name": "Soborite",
      "image_name": "SoboriteMain.jpg",
      "image_url": "https://static.wikitide.net/nmsgalactichubwiki/9/98/SoboriteMain.jpg",
      "galaxy": "Eissentam",
      "glyphs": "200BFA555C31",
      "civilization": "Legacy EisHub",
      "discovered_by": "",
      "discoverer_page": "ElCapoChino",
      "discoverer_url": "https://nmsgalactichub.miraheze.org/wiki/ElCapoChino"
    },
    {
      "page": "Soferite",
      "page_url": "https://nmsgalactichub.miraheze.org/wiki/Soferite",
      "name": "Soferite",
      "image_name": "SoferiteMain.jpg",
      "image_url": "https://static.wikitide.net/nmsgalactichubwiki/2/21/SoferiteMain.jpg",
      "galaxy": "Eissentam",
      "glyphs": "400BFA555C31",
      "civilization": "Legacy EisHub",
      "discovered_by": "",
      "discoverer_page": "ElCapoChino",
      "discoverer_url": "https://nmsgalactichub.miraheze.org/wiki/ElCapoChino"
    },
    {
      "page": "Sogdiasite",
      "page_url": "https://nmsgalactichub.miraheze.org/wiki/Sogdiasite",
      "name": "Sogdiasite",
      "image_name": "SogdiasiteMain.jpg",
      "image_url": "https://static.wikitide.net/nmsgalactichubwiki/3/3f/SogdiasiteMain.jpg",
      "galaxy": "Eissentam",
      "glyphs": "400BFA555C31",
      "civilization": "Legacy EisHub",
      "discovered_by": "",
      "discoverer_page": "ElCapoChino",
      "discoverer_url": "https://nmsgalactichub.miraheze.org/wiki/ElCapoChino"
    },
    {
      "page": "Tahalcite",
      "page_url": "https://nmsgalactichub.miraheze.org/wiki/Tahalcite",
      "name": "Tahalcite",
      "image_name": "275850_20250517155317_1.png",
      "image_url": "https://nmsgalactichub.miraheze.org/wiki/Special:FilePath/275850_20250517155317_1.png",
      "galaxy": "Eissentam",
      "glyphs": "60BD09556D30",
      "civilization": "Galactic Hub Eissentam",
      "discovered_by": "",
      "discoverer_page": "ApexFatality93",
      "discoverer_url": "https://nmsgalactichub.miraheze.org/wiki/ApexFatality93"
    },
    {
      "page": "Teburoite",
      "page_url": "https://nmsgalactichub.miraheze.org/wiki/Teburoite",
      "name": "Teburoite",
      "image_name": "TeburoiteMain.jpg",
      "image_url": "https://static.wikitide.net/nmsgalactichubwiki/d/d0/TeburoiteMain.jpg",
      "galaxy": "Eissentam",
      "glyphs": "000BFA555C31",
      "civilization": "Legacy EisHub",
      "discovered_by": "",
      "discoverer_page": "ElCapoChino",
      "discoverer_url": "https://nmsgalactichub.miraheze.org/wiki/ElCapoChino"
    },
    {
      "page": "Tetelkite",
      "page_url": "https://nmsgalactichub.miraheze.org/wiki/Tetelkite",
      "name": "Tetelkite",
      "image_name": "Screenshot (3237).png",
      "image_url": "https://static.wikitide.net/nmsgalactichubwiki/f/fa/Screenshot_%283237%29.png",
      "galaxy": "Calypso",
      "glyphs": "2220F9556C2F",
      "civilization": "Galactic Hub Calypso",
      "discovered_by": "",
      "discoverer_page": "Randomner",
      "discoverer_url": "https://nmsgalactichub.miraheze.org/wiki/Randomner"
    },
    {
      "page": "Tivanite",
      "page_url": "https://nmsgalactichub.miraheze.org/wiki/Tivanite",
      "name": "Tivanite",
      "image_name": "Tiva1.jpg",
      "image_url": "https://static.wikitide.net/nmsgalactichubwiki/d/dd/Tiva1.jpg",
      "galaxy": "Euclid",
      "glyphs": "2051F9556C2F",
      "civilization": "Legacy Galactic Hub",
      "discovered_by": "",
      "discoverer_page": "Donrhowland",
      "discoverer_url": "https://nmsgalactichub.miraheze.org/wiki/Donrhowland"
    },
    {
      "page": "Tozeraite",
      "page_url": "https://nmsgalactichub.miraheze.org/wiki/Tozeraite",
      "name": "Tozeraite",
      "image_name": "tozeraite.jpg",
      "image_url": "https://nmsgalactichub.miraheze.org/wiki/Special:FilePath/tozeraite.jpg",
      "galaxy": "Euclid",
      "glyphs": "1079CE589C1E",
      "civilization": "Galactic Hub Project",
      "discovered_by": "Sr. Kaio",
      "discoverer_page": "",
      "discoverer_url": ""
    },
    {
      "page": "Ugshaite",
      "page_url": "https://nmsgalactichub.miraheze.org/wiki/Ugshaite",
      "name": "Ugshaite",
      "image_name": "UgshaiteMain.jpg",
      "image_url": "https://static.wikitide.net/nmsgalactichubwiki/3/34/UgshaiteMain.jpg",
      "galaxy": "Eissentam",
      "glyphs": "400BFA555C31",
      "civilization": "Legacy EisHub",
      "discovered_by": "",
      "discoverer_page": "ElCapoChino",
      "discoverer_url": "https://nmsgalactichub.miraheze.org/wiki/ElCapoChino"
    },
    {
      "page": "Urlbuite",
      "page_url": "https://nmsgalactichub.miraheze.org/wiki/Urlbuite",
      "name": "Urlbuite",
      "image_name": "UrlbuiteMain.jpg",
      "image_url": "https://static.wikitide.net/nmsgalactichubwiki/8/8f/UrlbuiteMain.jpg",
      "galaxy": "Eissentam",
      "glyphs": "000BFA555C31",
      "civilization": "Legacy EisHub",
      "discovered_by": "",
      "discoverer_page": "ElCapoChino",
      "discoverer_url": "https://nmsgalactichub.miraheze.org/wiki/ElCapoChino"
    },
    {
      "page": "Ustilite",
      "page_url": "https://nmsgalactichub.miraheze.org/wiki/Ustilite",
      "name": "Ustilite",
      "image_name": "Usti1.jpg",
      "image_url": "https://static.wikitide.net/nmsgalactichubwiki/4/49/Usti1.jpg",
      "galaxy": "Euclid",
      "glyphs": "1051F9556C2F",
      "civilization": "Legacy Galactic Hub",
      "discovered_by": "",
      "discoverer_page": "Donrhowland",
      "discoverer_url": "https://nmsgalactichub.miraheze.org/wiki/Donrhowland"
    },
    {
      "page": "Vacelsoite",
      "page_url": "https://nmsgalactichub.miraheze.org/wiki/Vacelsoite",
      "name": "Vacelsoite",
      "image_name": "VacelsoiteMain.jpg",
      "image_url": "https://static.wikitide.net/nmsgalactichubwiki/a/ae/VacelsoiteMain.jpg",
      "galaxy": "Eissentam",
      "glyphs": "000BFA555C31",
      "civilization": "Legacy EisHub",
      "discovered_by": "",
      "discoverer_page": "ElCapoChino",
      "discoverer_url": "https://nmsgalactichub.miraheze.org/wiki/ElCapoChino"
    },
    {
      "page": "Vedoruite",
      "page_url": "https://nmsgalactichub.miraheze.org/wiki/Vedoruite",
      "name": "Vedoruite",
      "image_name": "Vedor1.jpg",
      "image_url": "https://static.wikitide.net/nmsgalactichubwiki/b/b2/Vedor1.jpg",
      "galaxy": "Euclid",
      "glyphs": "1051F9556C2F",
      "civilization": "Legacy Galactic Hub",
      "discovered_by": "",
      "discoverer_page": "Donrhowland",
      "discoverer_url": "https://nmsgalactichub.miraheze.org/wiki/Donrhowland"
    },
    {
      "page": "Videsite",
      "page_url": "https://nmsgalactichub.miraheze.org/wiki/Videsite",
      "name": "Videsite",
      "image_name": "VidesiteMain.jpg",
      "image_url": "https://static.wikitide.net/nmsgalactichubwiki/2/23/VidesiteMain.jpg",
      "galaxy": "Eissentam",
      "glyphs": "400BFA555C31",
      "civilization": "Legacy EisHub",
      "discovered_by": "",
      "discoverer_page": "ElCapoChino",
      "discoverer_url": "https://nmsgalactichub.miraheze.org/wiki/ElCapoChino"
    },
    {
      "page": "Yafsoite",
      "page_url": "https://nmsgalactichub.miraheze.org/wiki/Yafsoite",
      "name": "Yafsoite",
      "image_name": "Screenshot (3217).png",
      "image_url": "https://static.wikitide.net/nmsgalactichubwiki/5/58/Screenshot_%283217%29.png",
      "galaxy": "Calypso",
      "glyphs": "2220F9556C2F",
      "civilization": "Galactic Hub Calypso",
      "discovered_by": "",
      "discoverer_page": "Randomner",
      "discoverer_url": "https://nmsgalactichub.miraheze.org/wiki/Randomner"
    },
    {
      "page": "Yivanyuite",
      "page_url": "https://nmsgalactichub.miraheze.org/wiki/Yivanyuite",
      "name": "Yivanyuite",
      "image_name": "YivanyuiteMain.jpg",
      "image_url": "https://static.wikitide.net/nmsgalactichubwiki/a/a7/YivanyuiteMain.jpg",
      "galaxy": "Eissentam",
      "glyphs": "000BFA555C31",
      "civilization": "Legacy EisHub",
      "discovered_by": "",
      "discoverer_page": "ElCapoChino",
      "discoverer_url": "https://nmsgalactichub.miraheze.org/wiki/ElCapoChino"
    },
    {
      "page": "Zeunerite",
      "page_url": "https://nmsgalactichub.miraheze.org/wiki/Zeunerite",
      "name": "Zeunerite",
      "image_name": "ZeuneriteMain.jpg",
      "image_url": "https://static.wikitide.net/nmsgalactichubwiki/3/31/ZeuneriteMain.jpg",
      "galaxy": "Eissentam",
      "glyphs": "200BFA555C31",
      "civilization": "Legacy EisHub",
      "discovered_by": "",
      "discoverer_page": "ElCapoChino",
      "discoverer_url": "https://nmsgalactichub.miraheze.org/wiki/ElCapoChino"
    },
    {
      "page": "Zizerauite",
      "page_url": "https://nmsgalactichub.miraheze.org/wiki/Zizerauite",
      "name": "Zizerauite",
      "image_name": "Zizer1.jpg",
      "image_url": "https://static.wikitide.net/nmsgalactichubwiki/f/f5/Zizer1.jpg",
      "galaxy": "Euclid",
      "glyphs": "2051F9556C2F",
      "civilization": "Legacy Galactic Hub",
      "discovered_by": "",
      "discoverer_page": "Donrhowland",
      "discoverer_url": "https://nmsgalactichub.miraheze.org/wiki/Donrhowland"
    },
    {
      "page": "Zozartice",
      "page_url": "https://nmsgalactichub.miraheze.org/wiki/Zozartice",
      "name": "Zozartice",
      "image_name": "Zoza1.jpg",
      "image_url": "https://static.wikitide.net/nmsgalactichubwiki/2/2b/Zoza1.jpg",
      "galaxy": "Euclid",
      "glyphs": "3051F9556C2F",
      "civilization": "Legacy Galactic Hub",
      "discovered_by": "",
      "discoverer_page": "Donrhowland",
      "discoverer_url": "https://nmsgalactichub.miraheze.org/wiki/Donrhowland"
    }
  ]
}